{
    "key": "group_64a4855138d07",
    "title": "Hero | Main",
    "fields": [
        {
            "key": "field_64a7ed549a0a0",
            "label": "Background Image",
            "name": "background_image",
            "aria-label": "",
            "type": "image",
            "instructions": "",
            "required": 0,
            "conditional_logic": 0,
            "wrapper": {
                "width": "",
                "class": "",
                "id": ""
            },
            "acfe_save_meta": 0,
            "uploader": "",
            "return_format": "array",
            "acfe_thumbnail": 0,
            "min_width": "",
            "min_height": "",
            "min_size": "",
            "max_width": "",
            "max_height": "",
            "max_size": "",
            "mime_types": "",
            "preview_size": "medium",
            "library": "all"
        },
        {
            "key": "field_64a7dfa98adc1",
            "label": "Add title",
            "name": "add_title",
            "aria-label": "",
            "type": "repeater",
            "instructions": "Each new title line adds a line to the title",
            "required": 0,
            "conditional_logic": 0,
            "wrapper": {
                "width": "",
                "class": "",
                "id": ""
            },
            "acfe_save_meta": 0,
            "acfe_repeater_stylised_button": 0,
            "layout": "table",
            "pagination": 0,
            "min": 0,
            "max": 0,
            "collapsed": "",
            "button_label": "Add Title line",
            "rows_per_page": 20,
            "sub_fields": [
                {
                    "key": "field_64a7dfd48adc2",
                    "label": "Title",
                    "name": "title",
                    "aria-label": "",
                    "type": "text",
                    "instructions": "",
                    "required": 0,
                    "conditional_logic": 0,
                    "wrapper": {
                        "width": "",
                        "class": "",
                        "id": ""
                    },
                    "acfe_save_meta": 0,
                    "default_value": "",
                    "maxlength": "",
                    "placeholder": "",
                    "prepend": "",
                    "append": "",
                    "parent_repeater": "field_64a7dfa98adc1"
                }
            ]
        },
        {
            "key": "field_64a7dfde8adc3",
            "label": "Description",
            "name": "description",
            "aria-label": "",
            "type": "textarea",
            "instructions": "",
            "required": 0,
            "conditional_logic": 0,
            "wrapper": {
                "width": "",
                "class": "",
                "id": ""
            },
            "acfe_save_meta": 0,
            "default_value": "",
            "acfe_textarea_code": 0,
            "maxlength": "",
            "rows": 2,
            "placeholder": "",
            "new_lines": ""
        },
        {
            "key": "field_64a7dfed8adc4",
            "label": "Button",
            "name": "button",
            "aria-label": "",
            "type": "link",
            "instructions": "",
            "required": 0,
            "conditional_logic": 0,
            "wrapper": {
                "width": "",
                "class": "",
                "id": ""
            },
            "acfe_save_meta": 0,
            "return_format": "array"
        },
        {
            "key": "field_64a8047f14b23",
            "label": "Show Embed",
            "name": "show_embed",
            "aria-label": "",
            "type": "select",
            "instructions": "",
            "required": 0,
            "conditional_logic": 0,
            "wrapper": {
                "width": "",
                "class": "",
                "id": ""
            },
            "acfe_save_meta": 0,
            "choices": {
                "show": "Show",
                "hide": "Hide"
            },
            "default_value": "show",
            "return_format": "value",
            "multiple": 0,
            "allow_null": 0,
            "ui": 0,
            "ajax": 0,
            "placeholder": "",
            "allow_custom": 0,
            "search_placeholder": ""
        }
    ],
    "location": [
        [
            {
                "param": "post_type",
                "operator": "==",
                "value": "post"
            }
        ]
    ],
    "menu_order": 0,
    "position": "normal",
    "style": "default",
    "label_placement": "left",
    "instruction_placement": "label",
    "hide_on_screen": "",
    "active": true,
    "description": "",
    "show_in_rest": 0,
    "acfe_display_title": "",
    "acfe_autosync": [
        "json"
    ],
    "acfe_form": 0,
    "acfe_meta": "",
    "acfe_note": "",
    "modified": 1688732836,
    "acfe_categories": {
        "component": "Component"
    }
}
